<kml xmlns="http://www.opengis.net/kml/2.2" xmlns:gx="http://www.google.com/kml/ext/2.2" xmlns:xsi="http://www.w3.org/2001/XMLSchema-instance" xsi:schemaLocation="http://www.opengis.net/kml/2.2 https://developers.google.com/kml/schema/kml22gx.xsd"><Document><name>Zeichnung</name><Placemark id="linepolygon_1662546337889"><ExtendedData><Data name="htmlpopup"><value>&lt;div id="KML||https://public.geo.admin.ch/api/kml/files/gaJptzESS_WpnwmFJBchOg#linepolygon_1662546337889" class="htmlpopup-container"&gt;&lt;div class="htmlpopup-header"&gt;&lt;span&gt;Zeichnung &amp;nbsp;&lt;/span&gt;&lt;/div&gt;&lt;div class="htmlpopup-content"&gt;&lt;/div&gt;&lt;/div&gt;</value></Data><Data name="layerId"><value>KML||https://public.geo.admin.ch/api/kml/files/gaJptzESS_WpnwmFJBchOg</value></Data><Data name="type"><value>linepolygon</value></Data></ExtendedData><description></description><Style><LineStyle><color>ff0000ff</color><width>3</width></LineStyle><PolyStyle><color>660000ff</color></PolyStyle></Style><Polygon><outerBoundaryIs><LinearRing><coordinates>8.508271148507792,47.40590829940671 8.508380809016595,47.40604820348713 8.507679803491488,47.40628524930565 8.507574375280093,47.40614013719609 8.508271148507792,47.40590829940671</coordinates></LinearRing></outerBoundaryIs></Polygon></Placemark></Document></kml>